parkrun_to_sqlite/__init__.py
parkrun_to_sqlite/__main__.py
parkrun_to_sqlite/events.json
tests/__init__.py
tests/test_get_parkruns.py
parkrun_to_sqlite-0.7.dist-info/LICENSE
parkrun_to_sqlite-0.7.dist-info/METADATA
parkrun_to_sqlite-0.7.dist-info/WHEEL
parkrun_to_sqlite-0.7.dist-info/entry_points.txt
parkrun_to_sqlite-0.7.dist-info/top_level.txt
parkrun_to_sqlite-0.7.dist-info/RECORD
