Metadata-Version: 2.1
Name: parkrun-to-sqlite
Version: 0.7
Summary: Create a SQLite database containing your parkruns
Home-page: https://github.com/mwoodbri/parkrun-to-sqlite
Author: Mark Woodbridge
Author-email: mark.woodbridge@cantab.net
Classifier: Programming Language :: Python :: 3
Classifier: License :: OSI Approved :: MIT License
Classifier: Operating System :: OS Independent
Requires-Python: >=3.6
License-File: LICENSE
